schoolsoftapi/__init__.py
schoolsoftapi-0.3.0.dist-info/DESCRIPTION.rst
schoolsoftapi-0.3.0.dist-info/METADATA
schoolsoftapi-0.3.0.dist-info/RECORD
schoolsoftapi-0.3.0.dist-info/WHEEL
schoolsoftapi-0.3.0.dist-info/metadata.json
schoolsoftapi-0.3.0.dist-info/top_level.txt
