Metadata-Version: 2.0
Name: schoolsoftapi
Version: 0.3.0
Summary: SchooSoft API
Home-page: https://github.com/fossnio/schoolsoftapi
Author: William Wu
Author-email: william@pylabs.org
License: GPL 3
Platform: UNKNOWN
Classifier: Development Status :: 4 - Beta
Classifier: License :: OSI Approved :: GNU General Public License v3 (GPLv3)
Classifier: Programming Language :: Python :: 3
Requires-Dist: requests
Requires-Dist: xlrd
